<?xml version="1.0" encoding="utf-8"?>
<AirportWeather creationTime="2024-10-10T20:34:39" fullPackage="false" xmlns="http://aeec.aviation-ia.net/633" xmlns:xsi="http://www.w3.org/2001/XMLSchema-instance" xsi:schemaLocation="http://aeec.aviation-ia.net/633 AirportWeather.xsd">
    <M633Header timestamp="2024-10-10T20:34:39" versionNumber="3"/>
    <M633SupplementaryHeader>
        <Flight flightOriginDate="2024-10-11" scheduledTimeOfDeparture="2024-10-11T08:50:00Z">
            <FlightIdentification>
                <FlightIdentifier>LBT2807</FlightIdentifier>
                <FlightNumber airlineIATACode="BJ" number="2807">
                    <CommercialFlightNumber>BJ2807</CommercialFlightNumber>
                </FlightNumber>
            </FlightIdentification>
            <DepartureAirport>
                <AirportICAOCode>EDDV</AirportICAOCode>
                <AirportIATACode>HAJ</AirportIATACode>
            </DepartureAirport>
            <ArrivalAirport>
                <AirportICAOCode>DTTJ</AirportICAOCode>
                <AirportIATACode>DJE</AirportIATACode>
            </ArrivalAirport>
        </Flight>
        <Aircraft aircraftRegistration="TSINP">
            <AircraftModel>
                <AircraftICAOType>A320</AircraftICAOType>
            </AircraftModel>
        </Aircraft>
    </M633SupplementaryHeader>
    <WeatherBulletins>
        <WeatherBulletin sequence="1">
            <Airport airportName="DJERBA/ZARZIS" airportFunction="ArrivalAirport">
                <AirportICAOCode>DTTJ</AirportICAOCode>
                <AirportIATACode>DJE</AirportIATACode>
            </Airport>
            <Observation observationTime="2024-10-10T20:00:00" observationType="METAR">
                <ObservationDetails>
                    <SurfaceWinds>
                        <SurfaceWind>
                            <Directions>
                                <Direction>
                                    <Value type="true" unit="deg">50</Value>
                                </Direction>
                            </Directions>
                            <Speeds>
                                <Speed>
                                    <Value unit="kt">15</Value>
                                </Speed>
                            </Speeds>
                        </SurfaceWind>
                    </SurfaceWinds>
                    <VisibilitiesAndWeather>
                        <Visibilities>
                            <PrevailingVisibility>
                                <Value unit="m">8000</Value>
                            </PrevailingVisibility>
                        </Visibilities>
                        <Clouds>
                            <NilSignificantClouds/>
                        </Clouds>
                    </VisibilitiesAndWeather>
                    <Temperatures>
                        <AirTemperature>
                            <Value unit="C">28</Value>
                        </AirTemperature>
                        <DewPointTemperature>
                            <Value unit="C">23</Value>
                        </DewPointTemperature>
                    </Temperatures>
                    <Pressures>
                        <QNH>
                            <Value unit="hPa">1010</Value>
                        </QNH>
                    </Pressures>
                </ObservationDetails>
                <ObservationText>
                    <Paragraph sequence="1">
                        <Text>SA 102000 05015KT 8000 NSC 28/23 Q1010=</Text>
                    </Paragraph>
                </ObservationText>
            </Observation>
        </WeatherBulletin>
        <WeatherBulletin sequence="2">
            <Airport airportName="DJERBA/ZARZIS" airportFunction="ArrivalAirport">
                <AirportICAOCode>DTTJ</AirportICAOCode>
                <AirportIATACode>DJE</AirportIATACode>
            </Airport>
            <Forecast forecastTime="2024-10-10T17:00:00" forecastType="FT" forecastStartTime="2024-10-10T18:00:00" forecastEndTime="2024-10-11T18:00:00">
                <ForecastText>
                    <Paragraph sequence="1">
                        <Text>FT 101700 1018/1118 06006KT 8000 NSC</Text>
                    </Paragraph>
                    <Paragraph sequence="2">
                        <Text>PROB30 TEMPO 1019/1022 06020G30KT=</Text>
                    </Paragraph>
                </ForecastText>
            </Forecast>
        </WeatherBulletin>
        <WeatherBulletin sequence="3">
            <Airport airportName="HANNOVER" airportFunction="DepartureAirport">
                <AirportICAOCode>EDDV</AirportICAOCode>
                <AirportIATACode>HAJ</AirportIATACode>
            </Airport>
            <Observation observationTime="2024-10-10T20:20:00" observationType="METAR">
                <ObservationDetails>
                    <SurfaceWinds>
                        <SurfaceWind>
                            <Directions>
                                <Direction>
                                    <Value type="true" unit="deg">260</Value>
                                </Direction>
                            </Directions>
                            <Speeds>
                                <Speed>
                                    <Value unit="kt">6</Value>
                                </Speed>
                            </Speeds>
                        </SurfaceWind>
                    </SurfaceWinds>
                    <VisibilitiesAndWeather>
                        <Visibilities>
                            <PrevailingVisibility>
                                <Value unit="m">9999</Value>
                            </PrevailingVisibility>
                        </Visibilities>
                    </VisibilitiesAndWeather>
                    <Temperatures>
                        <AirTemperature>
                            <Value unit="C">9</Value>
                        </AirTemperature>
                        <DewPointTemperature>
                            <Value unit="C">5</Value>
                        </DewPointTemperature>
                    </Temperatures>
                    <Pressures>
                        <QNH>
                            <Value unit="hPa">1005</Value>
                        </QNH>
                    </Pressures>
                </ObservationDetails>
                <ObservationText>
                    <Paragraph sequence="1">
                        <Text>SA 102020 AUTO 26006KT CAVOK 09/05 Q1005 NOSIG=</Text>
                    </Paragraph>
                </ObservationText>
            </Observation>
        </WeatherBulletin>
        <WeatherBulletin sequence="4">
            <Airport airportName="HANNOVER" airportFunction="DepartureAirport">
                <AirportICAOCode>EDDV</AirportICAOCode>
                <AirportIATACode>HAJ</AirportIATACode>
            </Airport>
            <Forecast forecastTime="2024-10-10T17:00:00" forecastType="FT" forecastStartTime="2024-10-10T18:00:00" forecastEndTime="2024-10-11T18:00:00">
                <ForecastText>
                    <Paragraph sequence="1">
                        <Text>FT 101700 1018/1118 27008KT 9999 FEW030=</Text>
                    </Paragraph>
                </ForecastText>
            </Forecast>
        </WeatherBulletin>
        <WeatherBulletin sequence="5">
            <Airport airportName="MONASTIR/HABIB BOURGUIBA" airportFunction="PrimaryArrivalAlternateAirport">
                <AirportICAOCode>DTMB</AirportICAOCode>
                <AirportIATACode>MIR</AirportIATACode>
            </Airport>
            <Observation observationTime="2024-10-10T20:00:00" observationType="METAR">
                <ObservationDetails>
                    <SurfaceWinds>
                        <SurfaceWind>
                            <Directions>
                                <Direction>
                                    <Value type="true" unit="deg">-0</Value>
                                </Direction>
                            </Directions>
                            <Speeds>
                                <Speed>
                                    <Value unit="kt">13</Value>
                                </Speed>
                            </Speeds>
                        </SurfaceWind>
                    </SurfaceWinds>
                    <VisibilitiesAndWeather>
                        <Visibilities>
                            <PrevailingVisibility>
                                <Value unit="m">8000</Value>
                            </PrevailingVisibility>
                        </Visibilities>
                        <Clouds>
                            <NilSignificantClouds/>
                        </Clouds>
                    </VisibilitiesAndWeather>
                    <Temperatures>
                        <AirTemperature>
                            <Value unit="C">26</Value>
                        </AirTemperature>
                        <DewPointTemperature>
                            <Value unit="C">20</Value>
                        </DewPointTemperature>
                    </Temperatures>
                    <Pressures>
                        <QNH>
                            <Value unit="hPa">1012</Value>
                        </QNH>
                    </Pressures>
                </ObservationDetails>
                <ObservationText>
                    <Paragraph sequence="1">
                        <Text>SA 102000 36013KT 8000 NSC 26/20 Q1012=</Text>
                    </Paragraph>
                </ObservationText>
            </Observation>
        </WeatherBulletin>
        <WeatherBulletin sequence="6">
            <Airport airportName="MONASTIR/HABIB BOURGUIBA" airportFunction="PrimaryArrivalAlternateAirport">
                <AirportICAOCode>DTMB</AirportICAOCode>
                <AirportIATACode>MIR</AirportIATACode>
            </Airport>
            <Forecast forecastTime="2024-10-10T17:00:00" forecastType="FT" forecastStartTime="2024-10-10T18:00:00" forecastEndTime="2024-10-11T18:00:00">
                <ForecastText>
                    <Paragraph sequence="1">
                        <Text>FT 101700 1018/1118 07012KT 8000 FEW046</Text>
                    </Paragraph>
                    <Paragraph sequence="2">
                        <Text>BECMG 1022/1024 35015KT</Text>
                    </Paragraph>
                    <Paragraph sequence="3">
                        <Text>BECMG 1110/1112 04005KT=</Text>
                    </Paragraph>
                </ForecastText>
            </Forecast>
        </WeatherBulletin>
        <WeatherBulletin sequence="7">
            <Airport airportName="ENFIDHA / HAMMAMET" airportFunction="ArrivalAlternateAirport">
                <AirportICAOCode>DTNH</AirportICAOCode>
                <AirportIATACode>NBE</AirportIATACode>
            </Airport>
            <Observation observationTime="2024-10-10T20:00:00" observationType="METAR">
                <ObservationDetails>
                    <SurfaceWinds>
                        <SurfaceWind>
                            <Directions>
                                <Direction>
                                    <Value type="true" unit="deg">350</Value>
                                </Direction>
                            </Directions>
                            <Speeds>
                                <Speed>
                                    <Value unit="kt">10</Value>
                                </Speed>
                            </Speeds>
                        </SurfaceWind>
                    </SurfaceWinds>
                    <VisibilitiesAndWeather>
                        <Visibilities>
                            <PrevailingVisibility>
                                <Value unit="m">9999</Value>
                            </PrevailingVisibility>
                        </Visibilities>
                    </VisibilitiesAndWeather>
                    <Temperatures>
                        <AirTemperature>
                            <Value unit="C">25</Value>
                        </AirTemperature>
                        <DewPointTemperature>
                            <Value unit="C">18</Value>
                        </DewPointTemperature>
                    </Temperatures>
                    <Pressures>
                        <QNH>
                            <Value unit="hPa">1012</Value>
                        </QNH>
                    </Pressures>
                </ObservationDetails>
                <ObservationText>
                    <Paragraph sequence="1">
                        <Text>SA 102000 35010KT CAVOK 25/18 Q1012 NOSIG=</Text>
                    </Paragraph>
                </ObservationText>
            </Observation>
        </WeatherBulletin>
        <WeatherBulletin sequence="8">
            <Airport airportName="ENFIDHA / HAMMAMET" airportFunction="ArrivalAlternateAirport">
                <AirportICAOCode>DTNH</AirportICAOCode>
                <AirportIATACode>NBE</AirportIATACode>
            </Airport>
            <Forecast forecastTime="2024-10-10T17:00:00" forecastType="FT" forecastStartTime="2024-10-10T18:00:00" forecastEndTime="2024-10-11T18:00:00">
                <ForecastText>
                    <Paragraph sequence="1">
                        <Text>FT 101700 1018/1118 08010KT CAVOK</Text>
                    </Paragraph>
                    <Paragraph sequence="2">
                        <Text>BECMG 1022/1024 34010KT</Text>
                    </Paragraph>
                    <Paragraph sequence="3">
                        <Text>BECMG 1110/1112 04010KT=</Text>
                    </Paragraph>
                </ForecastText>
            </Forecast>
        </WeatherBulletin>
        <WeatherBulletin sequence="9">
            <Airport airportName="TUNIS/CARTHAGE" airportFunction="ArrivalAlternateAirport">
                <AirportICAOCode>DTTA</AirportICAOCode>
                <AirportIATACode>TUN</AirportIATACode>
            </Airport>
            <Observation observationTime="2024-10-10T20:00:00" observationType="METAR">
                <ObservationDetails>
                    <SurfaceWinds>
                        <SurfaceWind>
                            <Directions>
                                <Direction>
                                    <Value type="true" unit="deg">310</Value>
                                </Direction>
                            </Directions>
                            <Speeds>
                                <Speed>
                                    <Value unit="kt">9</Value>
                                </Speed>
                            </Speeds>
                        </SurfaceWind>
                    </SurfaceWinds>
                    <VisibilitiesAndWeather>
                        <Visibilities>
                            <PrevailingVisibility>
                                <Value unit="m">9999</Value>
                            </PrevailingVisibility>
                        </Visibilities>
                    </VisibilitiesAndWeather>
                    <Temperatures>
                        <AirTemperature>
                            <Value unit="C">24</Value>
                        </AirTemperature>
                        <DewPointTemperature>
                            <Value unit="C">20</Value>
                        </DewPointTemperature>
                    </Temperatures>
                    <Pressures>
                        <QNH>
                            <Value unit="hPa">1013</Value>
                        </QNH>
                    </Pressures>
                </ObservationDetails>
                <ObservationText>
                    <Paragraph sequence="1">
                        <Text>SA 102000 31009KT 9999 FEW040 24/20 Q1013=</Text>
                    </Paragraph>
                </ObservationText>
            </Observation>
        </WeatherBulletin>
        <WeatherBulletin sequence="10">
            <Airport airportName="TUNIS/CARTHAGE" airportFunction="ArrivalAlternateAirport">
                <AirportICAOCode>DTTA</AirportICAOCode>
                <AirportIATACode>TUN</AirportIATACode>
            </Airport>
            <Forecast forecastTime="2024-10-10T17:00:00" forecastType="FT" forecastStartTime="2024-10-10T18:00:00" forecastEndTime="2024-10-11T18:00:00">
                <ForecastText>
                    <Paragraph sequence="1">
                        <Text>FT 101700 1018/1118 31015KT 9999 FEW040</Text>
                    </Paragraph>
                    <Paragraph sequence="2">
                        <Text>BECMG 1101/1103 34005KT=</Text>
                    </Paragraph>
                </ForecastText>
            </Forecast>
        </WeatherBulletin>
        <WeatherBulletin sequence="11">
            <Airport airportName="PADERBORN-LIPPSTADT" airportFunction="EnRouteAlternateAirport">
                <AirportICAOCode>EDLP</AirportICAOCode>
                <AirportIATACode>PAD</AirportIATACode>
            </Airport>
            <Forecast forecastTime="2024-10-10T17:00:00" forecastType="FT" forecastStartTime="2024-10-10T18:00:00" forecastEndTime="2024-10-11T18:00:00">
                <ForecastText>
                    <Paragraph sequence="1">
                        <Text>FT 101700 1018/1118 26005KT 9999 SCT020</Text>
                    </Paragraph>
                    <Paragraph sequence="2">
                        <Text>TEMPO 1102/1108 BKN012</Text>
                    </Paragraph>
                    <Paragraph sequence="3">
                        <Text>PROB30 TEMPO 1103/1108 BKN007</Text>
                    </Paragraph>
                    <Paragraph sequence="4">
                        <Text>BECMG 1116/1118 VRB03KT=</Text>
                    </Paragraph>
                </ForecastText>
            </Forecast>
        </WeatherBulletin>
        <WeatherBulletin sequence="12">
            <Airport airportName="ERFURT-WEIMAR" airportFunction="EnRouteAlternateAirport">
                <AirportICAOCode>EDDE</AirportICAOCode>
                <AirportIATACode>ERF</AirportIATACode>
            </Airport>
            <Forecast forecastTime="2024-10-10T17:00:00" forecastType="FT" forecastStartTime="2024-10-10T18:00:00" forecastEndTime="2024-10-11T18:00:00">
                <ForecastText>
                    <Paragraph sequence="1">
                        <Text>FT 101700 1018/1118 28008KT 9999 SCT030</Text>
                    </Paragraph>
                    <Paragraph sequence="2">
                        <Text>PROB30 TEMPO 1101/1106 RA BKN014=</Text>
                    </Paragraph>
                </ForecastText>
            </Forecast>
        </WeatherBulletin>
        <WeatherBulletin sequence="13">
            <Airport airportName="DORTMUND" airportFunction="EnRouteAlternateAirport">
                <AirportICAOCode>EDLW</AirportICAOCode>
                <AirportIATACode>DTM</AirportIATACode>
            </Airport>
            <Forecast forecastTime="2024-10-10T17:00:00" forecastType="FT" forecastStartTime="2024-10-10T18:00:00" forecastEndTime="2024-10-11T18:00:00">
                <ForecastText>
                    <Paragraph sequence="1">
                        <Text>FT 101700 1018/1118 27005KT 9999 SCT040</Text>
                    </Paragraph>
                    <Paragraph sequence="2">
                        <Text>BECMG 1101/1104 21006KT</Text>
                    </Paragraph>
                    <Paragraph sequence="3">
                        <Text>TEMPO 1110/1114 27006KT</Text>
                    </Paragraph>
                    <Paragraph sequence="4">
                        <Text>BECMG 1114/1116 VRB03KT=</Text>
                    </Paragraph>
                </ForecastText>
            </Forecast>
        </WeatherBulletin>
        <WeatherBulletin sequence="14">
            <Airport airportName="MUNSTER/OSNABRUCK" airportFunction="EnRouteAlternateAirport">
                <AirportICAOCode>EDDG</AirportICAOCode>
                <AirportIATACode>FMO</AirportIATACode>
            </Airport>
            <Forecast forecastTime="2024-10-10T17:00:00" forecastType="FT" forecastStartTime="2024-10-10T18:00:00" forecastEndTime="2024-10-11T18:00:00">
                <ForecastText>
                    <Paragraph sequence="1">
                        <Text>FT 101700 1018/1118 29006KT 9999 SCT040</Text>
                    </Paragraph>
                    <Paragraph sequence="2">
                        <Text>BECMG 1018/1021 VRB03KT</Text>
                    </Paragraph>
                    <Paragraph sequence="3">
                        <Text>PROB30 TEMPO 1103/1105 4000 BCFG</Text>
                    </Paragraph>
                    <Paragraph sequence="4">
                        <Text>BECMG 1107/1110 24008KT</Text>
                    </Paragraph>
                    <Paragraph sequence="5">
                        <Text>BECMG 1115/1118 VRB02KT=</Text>
                    </Paragraph>
                </ForecastText>
            </Forecast>
        </WeatherBulletin>
        <WeatherBulletin sequence="15">
            <Airport airportName="LEIPZIG/HALLE" airportFunction="EnRouteAlternateAirport">
                <AirportICAOCode>EDDP</AirportICAOCode>
                <AirportIATACode>LEJ</AirportIATACode>
            </Airport>
            <Forecast forecastTime="2024-10-10T17:00:00" forecastType="FT" forecastStartTime="2024-10-10T18:00:00" forecastEndTime="2024-10-11T18:00:00">
                <ForecastText>
                    <Paragraph sequence="1">
                        <Text>FT 101700 1018/1118 28008KT 9999 SCT035=</Text>
                    </Paragraph>
                </ForecastText>
            </Forecast>
        </WeatherBulletin>
        <WeatherBulletin sequence="16">
            <Airport airportName="FRANKFURT/MAIN" airportFunction="EnRouteAlternateAirport">
                <AirportICAOCode>EDDF</AirportICAOCode>
                <AirportIATACode>FRA</AirportIATACode>
            </Airport>
            <Forecast forecastTime="2024-10-10T17:00:00" forecastType="FT" forecastStartTime="2024-10-10T18:00:00" forecastEndTime="2024-10-12T00:00:00">
                <ForecastText>
                    <Paragraph sequence="1">
                        <Text>FT 101700 1018/1124 28005KT 9999 SCT025 BKN040</Text>
                    </Paragraph>
                    <Paragraph sequence="2">
                        <Text>PROB40 TEMPO 1022/1104 4000 RA BKN014</Text>
                    </Paragraph>
                    <Paragraph sequence="3">
                        <Text>BECMG 1111/1114 SCT040</Text>
                    </Paragraph>
                    <Paragraph sequence="4">
                        <Text>BECMG 1115/1118 04004KT=</Text>
                    </Paragraph>
                </ForecastText>
            </Forecast>
        </WeatherBulletin>
        <WeatherBulletin sequence="17">
            <Airport airportName="BREMEN" airportFunction="EnRouteAlternateAirport">
                <AirportICAOCode>EDDW</AirportICAOCode>
                <AirportIATACode>BRE</AirportIATACode>
            </Airport>
            <Forecast forecastTime="2024-10-10T17:00:00" forecastType="FT" forecastStartTime="2024-10-10T18:00:00" forecastEndTime="2024-10-11T18:00:00">
                <ForecastText>
                    <Paragraph sequence="1">
                        <Text>FT 101700 1018/1118 27008KT 9999 FEW030=</Text>
                    </Paragraph>
                </ForecastText>
            </Forecast>
        </WeatherBulletin>
        <WeatherBulletin sequence="18">
            <Airport airportName="HAMBURG" airportFunction="EnRouteAlternateAirport">
                <AirportICAOCode>EDDH</AirportICAOCode>
                <AirportIATACode>HAM</AirportIATACode>
            </Airport>
            <Forecast forecastTime="2024-10-10T17:00:00" forecastType="FT" forecastStartTime="2024-10-10T18:00:00" forecastEndTime="2024-10-12T00:00:00">
                <ForecastText>
                    <Paragraph sequence="1">
                        <Text>FT 101700 1018/1124 26006KT 9999 FEW030</Text>
                    </Paragraph>
                    <Paragraph sequence="2">
                        <Text>PROB30 TEMPO 1018/1020 29013KT SHRA SCT025CB</Text>
                    </Paragraph>
                    <Paragraph sequence="3">
                        <Text>TEMPO 1110/1115 25013KT SHRA SCT020CB=</Text>
                    </Paragraph>
                </ForecastText>
            </Forecast>
        </WeatherBulletin>
        <WeatherBulletin sequence="19">
            <Airport airportName="EINDHOVEN" airportFunction="EnRouteAlternateAirport">
                <AirportICAOCode>EHEH</AirportICAOCode>
                <AirportIATACode>EIN</AirportIATACode>
            </Airport>
            <Forecast forecastTime="2024-10-10T17:34:00" forecastType="FT" forecastStartTime="2024-10-10T18:00:00" forecastEndTime="2024-10-12T00:00:00">
                <ForecastText>
                    <Paragraph sequence="1">
                        <Text>FT 101734 1018/1124 32006KT 9999 BKN045</Text>
                    </Paragraph>
                    <Paragraph sequence="2">
                        <Text>BECMG 1021/1023 28006KT</Text>
                    </Paragraph>
                    <Paragraph sequence="3">
                        <Text>PROB40 TEMPO 1023/1106 SCT020CB BKN030</Text>
                    </Paragraph>
                    <Paragraph sequence="4">
                        <Text>BECMG 1117/1119 11004KT=</Text>
                    </Paragraph>
                </ForecastText>
            </Forecast>
        </WeatherBulletin>
        <WeatherBulletin sequence="20">
            <Airport airportName="NURNBERG" airportFunction="EnRouteAlternateAirport">
                <AirportICAOCode>EDDN</AirportICAOCode>
                <AirportIATACode>NUE</AirportIATACode>
            </Airport>
            <Forecast forecastTime="2024-10-10T17:00:00" forecastType="FT" forecastStartTime="2024-10-10T18:00:00" forecastEndTime="2024-10-11T18:00:00">
                <ForecastText>
                    <Paragraph sequence="1">
                        <Text>FT 101700 1018/1118 24008KT 9999 BKN025</Text>
                    </Paragraph>
                    <Paragraph sequence="2">
                        <Text>TEMPO 1018/1020 SHRA FEW012 BKN020TCU</Text>
                    </Paragraph>
                    <Paragraph sequence="3">
                        <Text>PROB30 TEMPO 1023/1106 FEW004 BKN008</Text>
                    </Paragraph>
                    <Paragraph sequence="4">
                        <Text>BECMG 1104/1106 34008KT=</Text>
                    </Paragraph>
                </ForecastText>
            </Forecast>
        </WeatherBulletin>
        <WeatherBulletin sequence="21">
            <Airport airportName="COLOGNE/BONN" airportFunction="EnRouteAlternateAirport">
                <AirportICAOCode>EDDK</AirportICAOCode>
                <AirportIATACode>CGN</AirportIATACode>
            </Airport>
            <Forecast forecastTime="2024-10-10T17:00:00" forecastType="FT" forecastStartTime="2024-10-10T18:00:00" forecastEndTime="2024-10-12T00:00:00">
                <ForecastText>
                    <Paragraph sequence="1">
                        <Text>FT 101700 1018/1124 30006KT 9999 BKN020</Text>
                    </Paragraph>
                    <Paragraph sequence="2">
                        <Text>PROB30 TEMPO 1020/1101 RA BKN014</Text>
                    </Paragraph>
                    <Paragraph sequence="3">
                        <Text>BECMG 1100/1103 VRB03KT</Text>
                    </Paragraph>
                    <Paragraph sequence="4">
                        <Text>BECMG 1120/1123 12005KT=</Text>
                    </Paragraph>
                </ForecastText>
            </Forecast>
        </WeatherBulletin>
        <WeatherBulletin sequence="22">
            <Airport airportName="STUTTGART" airportFunction="EnRouteAlternateAirport">
                <AirportICAOCode>EDDS</AirportICAOCode>
                <AirportIATACode>STR</AirportIATACode>
            </Airport>
            <Forecast forecastTime="2024-10-10T17:00:00" forecastType="FT" forecastStartTime="2024-10-10T18:00:00" forecastEndTime="2024-10-11T18:00:00">
                <ForecastText>
                    <Paragraph sequence="1">
                        <Text>FT 101700 1018/1118 24004KT 9999 SCT040</Text>
                    </Paragraph>
                    <Paragraph sequence="2">
                        <Text>PROB30 TEMPO 1018/1104 SHRA BKN025CB</Text>
                    </Paragraph>
                    <Paragraph sequence="3">
                        <Text>BECMG 1106/1108 30005KT=</Text>
                    </Paragraph>
                </ForecastText>
            </Forecast>
        </WeatherBulletin>
        <WeatherBulletin sequence="23">
            <Airport airportName="MUNICH" airportFunction="EnRouteAlternateAirport">
                <AirportICAOCode>EDDM</AirportICAOCode>
                <AirportIATACode>MUC</AirportIATACode>
            </Airport>
            <Forecast forecastTime="2024-10-10T17:00:00" forecastType="FT" forecastStartTime="2024-10-10T18:00:00" forecastEndTime="2024-10-12T00:00:00">
                <ForecastText>
                    <Paragraph sequence="1">
                        <Text>FT 101700 1018/1124 24008KT 9999 BKN025</Text>
                    </Paragraph>
                    <Paragraph sequence="2">
                        <Text>PROB40 TEMPO 1018/1103 SHRA FEW013 BKN020TCU</Text>
                    </Paragraph>
                    <Paragraph sequence="3">
                        <Text>BECMG 1106/1108 32010KT</Text>
                    </Paragraph>
                    <Paragraph sequence="4">
                        <Text>PROB30 TEMPO 1106/1110 30015G25KT SHRA BKN020TCU</Text>
                    </Paragraph>
                    <Paragraph sequence="5">
                        <Text>BECMG 1112/1115 34005KT</Text>
                    </Paragraph>
                    <Paragraph sequence="6">
                        <Text>BECMG 1116/1118 VRB02KT=</Text>
                    </Paragraph>
                </ForecastText>
            </Forecast>
        </WeatherBulletin>
        <WeatherBulletin sequence="24">
            <Airport airportName="KARLSRUHE/BADEN-BADEN" airportFunction="EnRouteAlternateAirport">
                <AirportICAOCode>EDSB</AirportICAOCode>
                <AirportIATACode>FKB</AirportIATACode>
            </Airport>
            <Forecast forecastTime="2024-10-10T17:00:00" forecastType="FT" forecastStartTime="2024-10-10T18:00:00" forecastEndTime="2024-10-11T18:00:00">
                <ForecastText>
                    <Paragraph sequence="1">
                        <Text>FT 101700 1018/1118 26004KT 9999 SCT030 BKN040</Text>
                    </Paragraph>
                    <Paragraph sequence="2">
                        <Text>TEMPO 1018/1022 SHRA BKN025CB=</Text>
                    </Paragraph>
                </ForecastText>
            </Forecast>
        </WeatherBulletin>
        <WeatherBulletin sequence="25">
            <Airport airportName="SALZBURG" airportFunction="EnRouteAlternateAirport">
                <AirportICAOCode>LOWS</AirportICAOCode>
                <AirportIATACode>SZG</AirportIATACode>
            </Airport>
            <Forecast forecastTime="2024-10-10T17:15:00" forecastType="FT" forecastStartTime="2024-10-10T18:00:00" forecastEndTime="2024-10-11T18:00:00">
                <ForecastText>
                    <Paragraph sequence="1">
                        <Text>FT 101715 1018/1118 16007KT 9999 FEW060 BKN080 TX13/1111Z</Text>
                    </Paragraph>
                    <Paragraph sequence="2">
                        <Text>TN09/1103Z</Text>
                    </Paragraph>
                    <Paragraph sequence="3">
                        <Text>TEMPO 1102/1107 24005KT -SHRA</Text>
                    </Paragraph>
                    <Paragraph sequence="4">
                        <Text>BECMG 1107/1109 30008KT</Text>
                    </Paragraph>
                    <Paragraph sequence="5">
                        <Text>TEMPO 1110/1117 SHRA=</Text>
                    </Paragraph>
                </ForecastText>
            </Forecast>
        </WeatherBulletin>
        <WeatherBulletin sequence="26">
            <Airport airportName="LINZ" airportFunction="EnRouteAlternateAirport">
                <AirportICAOCode>LOWL</AirportICAOCode>
                <AirportIATACode>LNZ</AirportIATACode>
            </Airport>
            <Forecast forecastTime="2024-10-10T17:15:00" forecastType="FT" forecastStartTime="2024-10-10T18:00:00" forecastEndTime="2024-10-11T18:00:00">
                <ForecastText>
                    <Paragraph sequence="1">
                        <Text>FT 101715 1018/1118 26010KT 9999 SCT040 TX14/1113Z TN10/1118Z</Text>
                    </Paragraph>
                    <Paragraph sequence="2">
                        <Text>PROB40 TEMPO 1018/1022 3000 SHRA BKN010</Text>
                    </Paragraph>
                    <Paragraph sequence="3">
                        <Text>PROB30 TEMPO 1105/1115 -SHRA BKN012</Text>
                    </Paragraph>
                    <Paragraph sequence="4">
                        <Text>TEMPO 1110/1113 27015G25KT</Text>
                    </Paragraph>
                    <Paragraph sequence="5">
                        <Text>BECMG 1115/1117 30005KT=</Text>
                    </Paragraph>
                </ForecastText>
            </Forecast>
        </WeatherBulletin>
        <WeatherBulletin sequence="27">
            <Airport airportName="VERONA/VILLAFRANCA" airportFunction="EnRouteAlternateAirport">
                <AirportICAOCode>LIPX</AirportICAOCode>
                <AirportIATACode>VRN</AirportIATACode>
            </Airport>
            <Forecast forecastTime="2024-10-10T17:00:00" forecastType="FT" forecastStartTime="2024-10-10T18:00:00" forecastEndTime="2024-10-11T18:00:00">
                <ForecastText>
                    <Paragraph sequence="1">
                        <Text>FT 101700 1018/1118 VRB06KT 9999 SCT050=</Text>
                    </Paragraph>
                </ForecastText>
            </Forecast>
        </WeatherBulletin>
        <WeatherBulletin sequence="28">
            <Airport airportName="TRIESTE/RONCHI DEI LEGIONARI" airportFunction="EnRouteAlternateAirport">
                <AirportICAOCode>LIPQ</AirportICAOCode>
                <AirportIATACode>TRS</AirportIATACode>
            </Airport>
            <Forecast forecastTime="2024-10-10T17:00:00" forecastType="FT" forecastStartTime="2024-10-10T18:00:00" forecastEndTime="2024-10-11T18:00:00">
                <ForecastText>
                    <Paragraph sequence="1">
                        <Text>FT 101700 1018/1118 19012KT 9999 BKN040</Text>
                    </Paragraph>
                    <Paragraph sequence="2">
                        <Text>TEMPO 1018/1103 TSRA</Text>
                    </Paragraph>
                    <Paragraph sequence="3">
                        <Text>BECMG 1019/1021 06010KT=</Text>
                    </Paragraph>
                </ForecastText>
            </Forecast>
        </WeatherBulletin>
        <WeatherBulletin sequence="29">
            <Airport airportName="VENICE/TESSERA" airportFunction="EnRouteAlternateAirport">
                <AirportICAOCode>LIPZ</AirportICAOCode>
                <AirportIATACode>VCE</AirportIATACode>
            </Airport>
            <Forecast forecastTime="2024-10-10T17:00:00" forecastType="FT" forecastStartTime="2024-10-10T18:00:00" forecastEndTime="2024-10-12T00:00:00">
                <ForecastText>
                    <Paragraph sequence="1">
                        <Text>FT 101700 1018/1124 VRB05KT 9999 SCT030</Text>
                    </Paragraph>
                    <Paragraph sequence="2">
                        <Text>TEMPO 1018/1024 SHRA</Text>
                    </Paragraph>
                    <Paragraph sequence="3">
                        <Text>BECMG 1020/1022 03011KT=</Text>
                    </Paragraph>
                </ForecastText>
            </Forecast>
        </WeatherBulletin>
        <WeatherBulletin sequence="30">
            <Airport airportName="BRESCIA/MONTICHIARI" airportFunction="EnRouteAlternateAirport">
                <AirportICAOCode>LIPO</AirportICAOCode>
                <AirportIATACode>VBS</AirportIATACode>
            </Airport>
            <Forecast forecastTime="2024-10-10T17:00:00" forecastType="FT" forecastStartTime="2024-10-10T18:00:00" forecastEndTime="2024-10-11T18:00:00">
                <ForecastText>
                    <Paragraph sequence="1">
                        <Text>FT 101700 1018/1118 02005KT 9999 BKN013 BKN040</Text>
                    </Paragraph>
                    <Paragraph sequence="2">
                        <Text>BECMG 1019/1021 SCT020=</Text>
                    </Paragraph>
                </ForecastText>
            </Forecast>
        </WeatherBulletin>
        <WeatherBulletin sequence="31">
            <Airport airportName="BOLOGNA/BORGO PANIGALE" airportFunction="EnRouteAlternateAirport">
                <AirportICAOCode>LIPE</AirportICAOCode>
                <AirportIATACode>BLQ</AirportIATACode>
            </Airport>
            <Forecast forecastTime="2024-10-10T17:00:00" forecastType="FT" forecastStartTime="2024-10-10T18:00:00" forecastEndTime="2024-10-11T18:00:00">
                <ForecastText>
                    <Paragraph sequence="1">
                        <Text>FT 101700 1018/1118 VRB05KT 9999 SCT040=</Text>
                    </Paragraph>
                </ForecastText>
            </Forecast>
        </WeatherBulletin>
        <WeatherBulletin sequence="32">
            <Airport airportName="PARMA" airportFunction="EnRouteAlternateAirport">
                <AirportICAOCode>LIMP</AirportICAOCode>
                <AirportIATACode>PMF</AirportIATACode>
            </Airport>
            <Forecast forecastTime="2024-10-10T17:00:00" forecastType="FT" forecastStartTime="2024-10-10T18:00:00" forecastEndTime="2024-10-11T18:00:00">
                <ForecastText>
                    <Paragraph sequence="1">
                        <Text>FT 101700 1018/1118 29010KT 9999 SCT030</Text>
                    </Paragraph>
                    <Paragraph sequence="2">
                        <Text>BECMG 1018/1020 VRB05KT</Text>
                    </Paragraph>
                    <Paragraph sequence="3">
                        <Text>BECMG 1111/1113 08010KT</Text>
                    </Paragraph>
                    <Paragraph sequence="4">
                        <Text>BECMG 1115/1117 VRB05KT=</Text>
                    </Paragraph>
                </ForecastText>
            </Forecast>
        </WeatherBulletin>
        <WeatherBulletin sequence="33">
            <Airport airportName="BERGAMO/ORIO AL SERIO" airportFunction="EnRouteAlternateAirport">
                <AirportICAOCode>LIME</AirportICAOCode>
                <AirportIATACode>BGY</AirportIATACode>
            </Airport>
            <Forecast forecastTime="2024-10-10T17:00:00" forecastType="FT" forecastStartTime="2024-10-10T18:00:00" forecastEndTime="2024-10-11T18:00:00">
                <ForecastText>
                    <Paragraph sequence="1">
                        <Text>FT 101700 1018/1118 01006KT 9999 FEW020=</Text>
                    </Paragraph>
                </ForecastText>
            </Forecast>
        </WeatherBulletin>
        <WeatherBulletin sequence="34">
            <Airport airportName="FORLI" airportFunction="EnRouteAlternateAirport">
                <AirportICAOCode>LIPK</AirportICAOCode>
                <AirportIATACode>FRL</AirportIATACode>
            </Airport>
            <Forecast forecastTime="2024-10-10T17:00:00" forecastType="FT" forecastStartTime="2024-10-10T18:00:00" forecastEndTime="2024-10-11T18:00:00">
                <ForecastText>
                    <Paragraph sequence="1">
                        <Text>FT 101700 1018/1118 21010KT 9999 FEW040</Text>
                    </Paragraph>
                    <Paragraph sequence="2">
                        <Text>BECMG 1019/1021 VRB05KT</Text>
                    </Paragraph>
                    <Paragraph sequence="3">
                        <Text>TEMPO 1115/1118 SHRA=</Text>
                    </Paragraph>
                </ForecastText>
            </Forecast>
        </WeatherBulletin>
        <WeatherBulletin sequence="35">
            <Airport airportName="RIMINI/MIRAMARE" airportFunction="EnRouteAlternateAirport">
                <AirportICAOCode>LIPR</AirportICAOCode>
                <AirportIATACode>RMI</AirportIATACode>
            </Airport>
            <Forecast forecastTime="2024-10-10T17:00:00" forecastType="FT" forecastStartTime="2024-10-10T18:00:00" forecastEndTime="2024-10-11T18:00:00">
                <ForecastText>
                    <Paragraph sequence="1">
                        <Text>FT 101700 1018/1118 25010KT 9999 SCT040</Text>
                    </Paragraph>
                    <Paragraph sequence="2">
                        <Text>BECMG 1109/1111 31010KT=</Text>
                    </Paragraph>
                </ForecastText>
            </Forecast>
        </WeatherBulletin>
        <WeatherBulletin sequence="36">
            <Airport airportName="PULA" airportFunction="EnRouteAlternateAirport">
                <AirportICAOCode>LDPL</AirportICAOCode>
                <AirportIATACode>PUY</AirportIATACode>
            </Airport>
            <Forecast forecastTime="2024-10-10T17:25:00" forecastType="FT" forecastStartTime="2024-10-10T18:00:00" forecastEndTime="2024-10-11T18:00:00">
                <ForecastText>
                    <Paragraph sequence="1">
                        <Text>FT 101725 1018/1118 15008KT 9999 FEW010 SCT040 TX21/1112Z</Text>
                    </Paragraph>
                    <Paragraph sequence="2">
                        <Text>TN14/1105Z</Text>
                    </Paragraph>
                    <Paragraph sequence="3">
                        <Text>BECMG 1018/1020 24008KT</Text>
                    </Paragraph>
                    <Paragraph sequence="4">
                        <Text>PROB30 TEMPO 1023/1104 VRB15KT SHRA FEW030TCU BKN040</Text>
                    </Paragraph>
                    <Paragraph sequence="5">
                        <Text>BECMG 1100/1102 06012KT=</Text>
                    </Paragraph>
                </ForecastText>
            </Forecast>
        </WeatherBulletin>
        <WeatherBulletin sequence="37">
            <Airport airportName="PISA" airportFunction="EnRouteAlternateAirport">
                <AirportICAOCode>LIRP</AirportICAOCode>
                <AirportIATACode>PSA</AirportIATACode>
            </Airport>
            <Forecast forecastTime="2024-10-10T17:00:00" forecastType="FT" forecastStartTime="2024-10-10T18:00:00" forecastEndTime="2024-10-11T18:00:00">
                <ForecastText>
                    <Paragraph sequence="1">
                        <Text>FT 101700 1018/1118 24010KT 9999 SCT030</Text>
                    </Paragraph>
                    <Paragraph sequence="2">
                        <Text>BECMG 1102/1104 09005KT=</Text>
                    </Paragraph>
                </ForecastText>
            </Forecast>
        </WeatherBulletin>
        <WeatherBulletin sequence="38">
            <Airport airportName="ANCONA/FALCONARA MIL" airportFunction="EnRouteAlternateAirport">
                <AirportICAOCode>LIPY</AirportICAOCode>
                <AirportIATACode>AOI</AirportIATACode>
            </Airport>
            <Forecast forecastTime="2024-10-10T17:00:00" forecastType="FT" forecastStartTime="2024-10-10T18:00:00" forecastEndTime="2024-10-11T18:00:00">
                <ForecastText>
                    <Paragraph sequence="1">
                        <Text>FT 101700 1018/1118 23012KT 9999 SCT040</Text>
                    </Paragraph>
                    <Paragraph sequence="2">
                        <Text>BECMG 1108/1110 34012KT=</Text>
                    </Paragraph>
                </ForecastText>
            </Forecast>
        </WeatherBulletin>
        <WeatherBulletin sequence="39">
            <Airport airportName="ROME/FIUMICINO" airportFunction="EnRouteAlternateAirport">
                <AirportICAOCode>LIRF</AirportICAOCode>
                <AirportIATACode>FCO</AirportIATACode>
            </Airport>
            <Forecast forecastTime="2024-10-10T17:00:00" forecastType="FT" forecastStartTime="2024-10-10T18:00:00" forecastEndTime="2024-10-12T00:00:00">
                <ForecastText>
                    <Paragraph sequence="1">
                        <Text>FT 101700 1018/1124 27016KT 9999 SCT030</Text>
                    </Paragraph>
                    <Paragraph sequence="2">
                        <Text>TEMPO 1018/1020 4000 SHRA</Text>
                    </Paragraph>
                    <Paragraph sequence="3">
                        <Text>BECMG 1023/1101 05006KT</Text>
                    </Paragraph>
                    <Paragraph sequence="4">
                        <Text>BECMG 1110/1112 26012KT</Text>
                    </Paragraph>
                    <Paragraph sequence="5">
                        <Text>BECMG 1117/1120 04007KT=</Text>
                    </Paragraph>
                </ForecastText>
            </Forecast>
        </WeatherBulletin>
        <WeatherBulletin sequence="40">
            <Airport airportName="ROME/CIAMPINO" airportFunction="EnRouteAlternateAirport">
                <AirportICAOCode>LIRA</AirportICAOCode>
                <AirportIATACode>CIA</AirportIATACode>
            </Airport>
            <Forecast forecastTime="2024-10-10T17:00:00" forecastType="FT" forecastStartTime="2024-10-10T18:00:00" forecastEndTime="2024-10-11T18:00:00">
                <ForecastText>
                    <Paragraph sequence="1">
                        <Text>FT 101700 1018/1118 25015KT 9999 SCT025</Text>
                    </Paragraph>
                    <Paragraph sequence="2">
                        <Text>TEMPO 1018/1020 4000 SHRA</Text>
                    </Paragraph>
                    <Paragraph sequence="3">
                        <Text>BECMG 1019/1021 VRB05KT=</Text>
                    </Paragraph>
                </ForecastText>
            </Forecast>
        </WeatherBulletin>
        <WeatherBulletin sequence="41">
            <Airport airportName="PALERMO/PUNTA RAISI" airportFunction="EnRouteAlternateAirport">
                <AirportICAOCode>LICJ</AirportICAOCode>
                <AirportIATACode>PMO</AirportIATACode>
            </Airport>
            <Forecast forecastTime="2024-10-10T17:00:00" forecastType="FT" forecastStartTime="2024-10-10T18:00:00" forecastEndTime="2024-10-11T18:00:00">
                <ForecastText>
                    <Paragraph sequence="1">
                        <Text>FT 101700 1018/1118 26015KT 9999 SCT030=</Text>
                    </Paragraph>
                </ForecastText>
            </Forecast>
        </WeatherBulletin>
        <WeatherBulletin sequence="42">
            <Airport airportName="OLBIA/COSTA SMERALDA" airportFunction="EnRouteAlternateAirport">
                <AirportICAOCode>LIEO</AirportICAOCode>
                <AirportIATACode>OLB</AirportIATACode>
            </Airport>
            <Forecast forecastTime="2024-10-10T17:00:00" forecastType="FT" forecastStartTime="2024-10-10T18:00:00" forecastEndTime="2024-10-11T18:00:00">
                <ForecastText>
                    <Paragraph sequence="1">
                        <Text>FT 101700 1018/1118 25018G30KT 9999 FEW030</Text>
                    </Paragraph>
                    <Paragraph sequence="2">
                        <Text>BECMG 1020/1022 26016KT=</Text>
                    </Paragraph>
                </ForecastText>
            </Forecast>
        </WeatherBulletin>
        <WeatherBulletin sequence="43">
            <Airport airportName="BASTIA/PORETTA" airportFunction="EnRouteAlternateAirport">
                <AirportICAOCode>LFKB</AirportICAOCode>
                <AirportIATACode>BIA</AirportIATACode>
            </Airport>
            <Forecast forecastTime="2024-10-10T20:00:00" forecastType="FT" forecastStartTime="2024-10-10T21:00:00" forecastEndTime="2024-10-11T21:00:00">
                <ForecastText>
                    <Paragraph sequence="1">
                        <Text>FT 102000 1021/1121 24005KT CAVOK TX24/1112Z TN14/1104Z</Text>
                    </Paragraph>
                    <Paragraph sequence="2">
                        <Text>BECMG 1110/1112 10006KT</Text>
                    </Paragraph>
                    <Paragraph sequence="3">
                        <Text>BECMG 1118/1120 24003KT=</Text>
                    </Paragraph>
                </ForecastText>
            </Forecast>
        </WeatherBulletin>
        <WeatherBulletin sequence="44">
            <Airport airportName="BISKRA/MOHAMED KHIDER" airportFunction="EnRouteAlternateAirport">
                <AirportICAOCode>DAUB</AirportICAOCode>
                <AirportIATACode>BSK</AirportIATACode>
            </Airport>
            <Forecast forecastTime="2024-10-10T17:00:00" forecastType="FT" forecastStartTime="2024-10-10T18:00:00" forecastEndTime="2024-10-11T18:00:00">
                <ForecastText>
                    <Paragraph sequence="1">
                        <Text>FT 101700 1018/1118 32014KT 6000 NSC</Text>
                    </Paragraph>
                    <Paragraph sequence="2">
                        <Text>PROB40 TEMPO 1018/1022 32015G30KT 3000 DRSA</Text>
                    </Paragraph>
                    <Paragraph sequence="3">
                        <Text>BECMG 1020/1023 20008KT=</Text>
                    </Paragraph>
                </ForecastText>
            </Forecast>
        </WeatherBulletin>
        <WeatherBulletin sequence="45">
            <Airport airportName="SFAX/THYNA" airportFunction="EnRouteAlternateAirport">
                <AirportICAOCode>DTTX</AirportICAOCode>
                <AirportIATACode>SFA</AirportIATACode>
            </Airport>
            <Forecast forecastTime="2024-10-10T17:00:00" forecastType="FT" forecastStartTime="2024-10-10T18:00:00" forecastEndTime="2024-10-11T18:00:00">
                <ForecastText>
                    <Paragraph sequence="1">
                        <Text>FT 101700 1018/1118 02006KT 9999 FEW030</Text>
                    </Paragraph>
                    <Paragraph sequence="2">
                        <Text>BECMG 1021/1023 04010KT=</Text>
                    </Paragraph>
                </ForecastText>
            </Forecast>
        </WeatherBulletin>
        <WeatherBulletin sequence="46">
            <Airport airportName="LAMPEDUSA" airportFunction="EnRouteAlternateAirport">
                <AirportICAOCode>LICD</AirportICAOCode>
                <AirportIATACode>LMP</AirportIATACode>
            </Airport>
            <Forecast forecastTime="2024-10-10T17:00:00" forecastType="FT" forecastStartTime="2024-10-10T18:00:00" forecastEndTime="2024-10-11T18:00:00">
                <ForecastText>
                    <Paragraph sequence="1">
                        <Text>FT 101700 1018/1118 36013KT 9999 SCT010=</Text>
                    </Paragraph>
                </ForecastText>
            </Forecast>
        </WeatherBulletin>
        <WeatherBulletin sequence="47">
            <Airport airportName="SETIF/8 MAI 45" airportFunction="EnRouteAlternateAirport">
                <AirportICAOCode>DAAS</AirportICAOCode>
                <AirportIATACode>QSF</AirportIATACode>
            </Airport>
            <Forecast forecastTime="2024-10-10T17:00:00" forecastType="FT" forecastStartTime="2024-10-10T18:00:00" forecastEndTime="2024-10-11T18:00:00">
                <ForecastText>
                    <Paragraph sequence="1">
                        <Text>FT 101700 1018/1118 34008KT 9999 FEW030=</Text>
                    </Paragraph>
                </ForecastText>
            </Forecast>
        </WeatherBulletin>
        <WeatherBulletin sequence="48">
            <Airport airportName="ZARZAITINE/IN AMENAS" airportFunction="EnRouteAlternateAirport">
                <AirportICAOCode>DAUZ</AirportICAOCode>
                <AirportIATACode>IAM</AirportIATACode>
            </Airport>
            <Forecast forecastTime="2024-10-10T17:00:00" forecastType="FT" forecastStartTime="2024-10-10T18:00:00" forecastEndTime="2024-10-11T18:00:00">
                <ForecastText>
                    <Paragraph sequence="1">
                        <Text>FT 101700 1018/1118 22010KT 9999 FEW046</Text>
                    </Paragraph>
                    <Paragraph sequence="2">
                        <Text>PROB30 TEMPO 1018/1022 22015G25KT FEW033CB</Text>
                    </Paragraph>
                    <Paragraph sequence="3">
                        <Text>BECMG 1020/1023 VRB02KT=</Text>
                    </Paragraph>
                </ForecastText>
            </Forecast>
        </WeatherBulletin>
    </WeatherBulletins>
</AirportWeather>
