<?xml version="1.0" encoding="UTF-8"?>
<RaimBriefing xmlns:xsi="http://www.w3.org/2001/XMLSchema-instance" effectiveTill="2024-07-25T02:26:55Z" effectiveFrom="2024-07-24T20:15:00Z" creationTime="2024-07-24T16:51:21.311Z" predictionStatus="PredictionDataFound" xsi:noNamespaceSchemaLocation="RaimBriefingEFF.xsd">
 <RaimPositions>
  <Airport airportName="IRAKLION/NIKOS KAZANTZAKIS" iataCode="HER" icaoCode="LGIR">
   <AirportRole sequence="16" priority="1" effectiveFrom="2024-07-24T21:57:06Z" effectiveTill="2024-07-25T00:57:06Z" airportCategory="EnrouteAirport">
    <Outages maskAngle="5.0" baroAided="true" integrityLevel="0.3"/>
   </AirportRole>
  </Airport>
  <Airport airportName="KOS/IPPOKRATIS" iataCode="KGS" icaoCode="LGKO">
   <AirportRole sequence="16" priority="1" effectiveFrom="2024-07-24T21:54:34Z" effectiveTill="2024-07-25T00:54:34Z" airportCategory="EnrouteAirport">
    <Outages maskAngle="5.0" baroAided="true" integrityLevel="0.3"/>
   </AirportRole>
  </Airport>
  <Airport airportName="CATANIA/FONTANAROSSA" iataCode="CTA" icaoCode="LICC">
   <AirportRole sequence="16" priority="1" effectiveFrom="2024-07-24T21:21:39Z" effectiveTill="2024-07-25T00:21:39Z" airportCategory="EnrouteAirport">
    <Outages maskAngle="5.0" baroAided="true" integrityLevel="0.3"/>
   </AirportRole>
  </Airport>
  <Airport airportName="MALTA/LUQA" iataCode="MLA" icaoCode="LMML">
   <AirportRole sequence="16" priority="1" effectiveFrom="2024-07-24T20:48:53Z" effectiveTill="2024-07-24T23:48:53Z" airportCategory="EnrouteAirport">
    <Outages maskAngle="5.0" baroAided="true" integrityLevel="0.3"/>
   </AirportRole>
  </Airport>
  <Airport airportName="ANKARA/ESENBOGA INTL" iataCode="ESB" icaoCode="LTAC">
   <AirportRole sequence="5" priority="1" effectiveFrom="2024-07-24T22:28:27Z" effectiveTill="2024-07-25T00:28:27Z" airportCategory="AlternateAirport">
    <Outages maskAngle="5.0" baroAided="true" integrityLevel="0.3"/>
    <Outages maskAngle="5.0" baroAided="true" integrityLevel="1.0"/>
   </AirportRole>
  </Airport>
  <Airport airportName="MUGLA/DALAMAN" iataCode="DLM" icaoCode="LTBS">
   <AirportRole sequence="16" priority="1" effectiveFrom="2024-07-24T21:52:57Z" effectiveTill="2024-07-25T00:52:57Z" airportCategory="EnrouteAirport">
    <Outages maskAngle="5.0" baroAided="true" integrityLevel="0.3"/>
   </AirportRole>
  </Airport>
  <Airport airportName="AMMAN MARKA INTL" iataCode="ADJ" icaoCode="OJAM">
   <AirportRole sequence="16" priority="1" effectiveFrom="2024-07-24T23:11:42Z" effectiveTill="2024-07-25T02:11:42Z" airportCategory="EnrouteAirport">
    <Outages maskAngle="5.0" baroAided="true" integrityLevel="0.3"/>
   </AirportRole>
  </Airport>
  <Airport airportName="BEIRUT/RAFIC HARIRI INTL" iataCode="BEY" icaoCode="OLBA">
   <AirportRole sequence="16" priority="1" effectiveFrom="2024-07-24T22:33:27Z" effectiveTill="2024-07-25T01:33:27Z" airportCategory="EnrouteAirport">
    <Outages maskAngle="5.0" baroAided="true" integrityLevel="0.3"/>
   </AirportRole>
  </Airport>
  <Airport airportName="LAMPEDUSA" iataCode="LMP" icaoCode="LICD">
   <AirportRole sequence="16" priority="1" effectiveFrom="2024-07-24T20:45:36Z" effectiveTill="2024-07-24T23:45:36Z" airportCategory="EnrouteAirport">
    <Outages maskAngle="5.0" baroAided="true" integrityLevel="0.3"/>
   </AirportRole>
  </Airport>
  <Airport airportName="SANTORINI" iataCode="JTR" icaoCode="LGSR">
   <AirportRole sequence="16" priority="1" effectiveFrom="2024-07-24T21:57:26Z" effectiveTill="2024-07-25T00:57:26Z" airportCategory="EnrouteAirport">
    <Outages maskAngle="5.0" baroAided="true" integrityLevel="0.3"/>
   </AirportRole>
  </Airport>
  <Airport airportName="MERSA MATRUH" iataCode="MUH" icaoCode="HEMM">
   <AirportRole sequence="16" priority="1" effectiveFrom="2024-07-24T22:23:08Z" effectiveTill="2024-07-25T01:23:08Z" airportCategory="EnrouteAirport">
    <Outages maskAngle="5.0" baroAided="true" integrityLevel="0.3"/>
   </AirportRole>
  </Airport>
  <Airport airportName="MILAS/BODRUM" iataCode="BJV" icaoCode="LTFE">
   <AirportRole sequence="5" priority="1" effectiveFrom="2024-07-24T22:26:54Z" effectiveTill="2024-07-25T00:26:54Z" airportCategory="AlternateAirport">
    <Outages maskAngle="5.0" baroAided="true" integrityLevel="0.3"/>
   </AirportRole>
   <AirportRole usedApproach="VORDME" sequence="16" priority="2" effectiveFrom="2024-07-24T21:54:53Z" effectiveTill="2024-07-25T00:54:53Z" airportCategory="EnrouteAirport">
    <Outages maskAngle="5.0" baroAided="true" integrityLevel="0.3"/>
   </AirportRole>
  </Airport>
  <Airport airportName="ALEXANDRIA/BORG EL ARAB INTL" iataCode="HBE" icaoCode="HEBA">
   <AirportRole sequence="16" priority="1" effectiveFrom="2024-07-24T22:26:43Z" effectiveTill="2024-07-25T01:26:43Z" airportCategory="EnrouteAirport">
    <Outages maskAngle="5.0" baroAided="true" integrityLevel="0.3"/>
   </AirportRole>
  </Airport>
  <Airport airportName="ATHENS/ELEFTHERIOS VENIZELOS" iataCode="ATH" icaoCode="LGAV">
   <AirportRole sequence="16" priority="1" effectiveFrom="2024-07-24T21:15:27Z" effectiveTill="2024-07-25T00:15:27Z" airportCategory="EnrouteAirport">
    <Outages maskAngle="5.0" baroAided="true" integrityLevel="0.3"/>
    <Outages maskAngle="5.0" baroAided="true" integrityLevel="1.0"/>
   </AirportRole>
  </Airport>
  <Airport airportName="ISTANBUL AIRPORT" iataCode="IST" icaoCode="LTFM">
   <AirportRole sequence="5" priority="1" effectiveFrom="2024-07-24T22:40:45Z" effectiveTill="2024-07-25T00:40:45Z" airportCategory="AlternateAirport">
    <Outages maskAngle="5.0" baroAided="true" integrityLevel="0.3"/>
    <Outages maskAngle="5.0" baroAided="true" integrityLevel="1.0"/>
   </AirportRole>
  </Airport>
 </RaimPositions>
 <Flight airlineICAOCode="LBT" airlineIATACode="BJ" number="4528" date="2024-07-24Z">
  <DepartureAirport iataCode="TUN" icaoCode="DTTA"/>
  <DestinationAirport iataCode="AYT" icaoCode="LTAI"/>
 </Flight>
 <Satellites minimumNumber="31"/>
</RaimBriefing>
