<?xml version="1.0" encoding="UTF-8"?>
<AirspaceData flightPlanId="OFP7" xsi:schemaLocation="http://aeec.aviation-ia.net/633 AirspaceData.xsd" xmlns="http://aeec.aviation-ia.net/633" xmlns:xsi="http://www.w3.org/2001/XMLSchema-instance">
<M633Header timestamp="2024-11-25T03:47:23Z" versionNumber="3"/> 
<M633SupplementaryHeader>
    <Flight flightOriginDate="2024-11-25Z" scheduledTimeOfDeparture="2024-11-25T06:30:00Z">
        <FlightIdentification>
            <FlightIdentifier>LBT542</FlightIdentifier>
                <FlightNumber airlineIATACode="BJ" number="542" >
                    <CommercialFlightNumber>BJ542</CommercialFlightNumber>
                </FlightNumber>
             </FlightIdentification>
        <DepartureAirport airportFunction="DepartureAirport" airportName="MONASTIR/HABIB BOURGUIBA">
            <AirportICAOCode>DTMB</AirportICAOCode>
            <AirportIATACode>MIR</AirportIATACode>
        </DepartureAirport>
        <ArrivalAirport airportFunction="ArrivalAirport" airportName="PARIS/CHARLES DE GAULLE">
            <AirportICAOCode>LFPG</AirportICAOCode>
            <AirportIATACode>CDG</AirportIATACode>
        </ArrivalAirport>
    </Flight>
    <Aircraft aircraftRegistration="TSINF" >
        <AircraftModel airlineSpecificSubType="1.11">
            <AircraftICAOType>A320</AircraftICAOType>
        </AircraftModel>
    </Aircraft>
</M633SupplementaryHeader>
    <Airspace airspaceName="TUNIS_FIR" airspaceType="FIR" airspaceICAOCode="DTTC">
        <Entry cumulatedFlightTime="PT0H0M00S">
            <Coordinates latitude="+128729" longitude="+38717">N3545.5 E01045.3</Coordinates>
            <CumulatedGroundDistance unit="NM">0</CumulatedGroundDistance>
        </Entry>
        <Exit cumulatedFlightTime="PT0H12M52S">
            <Coordinates  latitude="+132180" longitude="+37063">N3643.0 E01017.7</Coordinates>
            <CumulatedGroundDistance unit="NM">71</CumulatedGroundDistance>
        </Exit>
        <GroundDistance unit="NM">0</GroundDistance>
    </Airspace>
    <Airspace airspaceName="TUNIS_UIR" airspaceType="UIR" airspaceICAOCode="DTTC">
        <Entry cumulatedFlightTime="PT0H12M52S">
            <Coordinates latitude="+132180" longitude="+37063">N3643.0 E01017.7</Coordinates>
            <CumulatedGroundDistance unit="NM">71</CumulatedGroundDistance>
        </Entry>
        <Exit cumulatedFlightTime="PT0H25M14S">
            <Coordinates  latitude="+137717" longitude="+35234">N3815.3 E00947.2</Coordinates>
            <CumulatedGroundDistance unit="NM">166</CumulatedGroundDistance>
        </Exit>
        <GreatCircleDistance unit="NM">71</GreatCircleDistance>
        <GroundDistance unit="NM">71</GroundDistance>
    </Airspace>
    <Airspace airspaceName="ROME_UIR" airspaceType="UIR" airspaceICAOCode="LIRR">
        <Entry cumulatedFlightTime="PT0H25M14S">
            <Coordinates latitude="+137717" longitude="+35234">N3815.3 E00947.2</Coordinates>
            <CumulatedGroundDistance unit="NM">166</CumulatedGroundDistance>
        </Entry>
        <Exit cumulatedFlightTime="PT0H49M35S">
            <Coordinates  latitude="+148800" longitude="+31724">N4120.0 E00848.7</Coordinates>
            <CumulatedGroundDistance unit="NM">357</CumulatedGroundDistance>
        </Exit>
        <GreatCircleDistance unit="NM">166</GreatCircleDistance>
        <GroundDistance unit="NM">166</GroundDistance>
    </Airspace>
    <Airspace airspaceName="FRANCE_UIR" airspaceType="UIR" airspaceICAOCode="LFFF">
        <Entry cumulatedFlightTime="PT0H49M35S">
            <Coordinates latitude="+148800" longitude="+31724">N4120.0 E00848.7</Coordinates>
            <CumulatedGroundDistance unit="NM">357</CumulatedGroundDistance>
        </Entry>
        <Exit cumulatedFlightTime="PT1H58M11S">
            <Coordinates  latitude="+174470" longitude="+12805">N4827.8 E00333.4</Coordinates>
            <CumulatedGroundDistance unit="NM">880</CumulatedGroundDistance>
        </Exit>
        <GreatCircleDistance unit="NM">356</GreatCircleDistance>
        <GroundDistance unit="NM">357</GroundDistance>
    </Airspace>
    <Airspace airspaceName="PARIS_FIR" airspaceType="FIR" airspaceICAOCode="LFFF">
        <Entry cumulatedFlightTime="PT1H58M11S">
            <Coordinates latitude="+174470" longitude="+12805">N4827.8 E00333.4</Coordinates>
            <CumulatedGroundDistance unit="NM">880</CumulatedGroundDistance>
        </Entry>
        <Exit cumulatedFlightTime="PT2H12M44S">
            <Coordinates  latitude="+176435" longitude="+9172">N4900.6 E00232.9</Coordinates>
            <CumulatedGroundDistance unit="NM">947</CumulatedGroundDistance>
        </Exit>
        <GreatCircleDistance unit="NM">855</GreatCircleDistance>
        <GroundDistance unit="NM">880</GroundDistance>
    </Airspace>
</AirspaceData>