<?xml version="1.0" encoding="UTF-8"?>
<AirspaceData flightPlanId="OFP11" xsi:schemaLocation="http://aeec.aviation-ia.net/633 AirspaceData.xsd" xmlns="http://aeec.aviation-ia.net/633" xmlns:xsi="http://www.w3.org/2001/XMLSchema-instance">
<M633Header timestamp="2024-08-04T00:13:32Z" versionNumber="3"/> 
<M633SupplementaryHeader>
    <Flight flightOriginDate="2024-08-04Z" scheduledTimeOfDeparture="2024-08-04T01:00:00Z">
        <FlightIdentification>
            <FlightIdentifier>LBT7470</FlightIdentifier>
                <FlightNumber airlineIATACode="BJ" number="7470" >
                    <CommercialFlightNumber>BJ7470</CommercialFlightNumber>
                </FlightNumber>
             </FlightIdentification>
        <DepartureAirport airportFunction="DepartureAirport" airportName="MONASTIR/HABIB BOURGUIBA">
            <AirportICAOCode>DTMB</AirportICAOCode>
            <AirportIATACode>MIR</AirportIATACode>
        </DepartureAirport>
        <ArrivalAirport airportFunction="ArrivalAirport" airportName="KATOWICE/PYRZOWICE">
            <AirportICAOCode>EPKT</AirportICAOCode>
            <AirportIATACode>KTW</AirportIATACode>
        </ArrivalAirport>
    </Flight>
    <Aircraft aircraftRegistration="TSINH" >
        <AircraftModel airlineSpecificSubType="5.93">
            <AircraftICAOType>A320</AircraftICAOType>
        </AircraftModel>
    </Aircraft>
</M633SupplementaryHeader>
    <Airspace airspaceName="TUNIS_FIR" airspaceType="FIR" airspaceICAOCode="DTTC">
        <Entry cumulatedFlightTime="PT0H0M00S">
            <Coordinates latitude="+128729" longitude="+38717">N3545.5 E01045.3</Coordinates>
            <CumulatedGroundDistance unit="NM">0</CumulatedGroundDistance>
        </Entry>
        <Exit cumulatedFlightTime="PT0H13M24S">
            <Coordinates  latitude="+131751" longitude="+41221">N3635.8 E01127.0</Coordinates>
            <CumulatedGroundDistance unit="NM">75</CumulatedGroundDistance>
        </Exit>
        <GroundDistance unit="NM">0</GroundDistance>
    </Airspace>
    <Airspace airspaceName="TUNIS_UIR" airspaceType="UIR" airspaceICAOCode="DTTC">
        <Entry cumulatedFlightTime="PT0H13M24S">
            <Coordinates latitude="+131751" longitude="+41221">N3635.8 E01127.0</Coordinates>
            <CumulatedGroundDistance unit="NM">75</CumulatedGroundDistance>
        </Entry>
        <Exit cumulatedFlightTime="PT0H15M30S">
            <Coordinates  latitude="+132623" longitude="+41400">N3650.4 E01130.0</Coordinates>
            <CumulatedGroundDistance unit="NM">89</CumulatedGroundDistance>
        </Exit>
        <GreatCircleDistance unit="NM">68</GreatCircleDistance>
        <GroundDistance unit="NM">75</GroundDistance>
    </Airspace>
    <Airspace airspaceName="ROME_UIR" airspaceType="UIR" airspaceICAOCode="LIRR">
        <Entry cumulatedFlightTime="PT0H15M30S">
            <Coordinates latitude="+132623" longitude="+41400">N3650.4 E01130.0</Coordinates>
            <CumulatedGroundDistance unit="NM">89</CumulatedGroundDistance>
        </Entry>
        <Exit cumulatedFlightTime="PT1H2M00S">
            <Coordinates  latitude="+152455" longitude="+48944">N4220.9 E01335.7</Coordinates>
            <CumulatedGroundDistance unit="NM">436</CumulatedGroundDistance>
        </Exit>
        <GreatCircleDistance unit="NM">81</GreatCircleDistance>
        <GroundDistance unit="NM">89</GroundDistance>
    </Airspace>
    <Airspace airspaceName="BRINDISI_UIR" airspaceType="UIR" airspaceICAOCode="LIBB">
        <Entry cumulatedFlightTime="PT1H2M00S">
            <Coordinates latitude="+152455" longitude="+48944">N4220.9 E01335.7</Coordinates>
            <CumulatedGroundDistance unit="NM">436</CumulatedGroundDistance>
        </Entry>
        <Exit cumulatedFlightTime="PT1H11M32S">
            <Coordinates  latitude="+156628" longitude="+50604">N4330.5 E01403.4</Coordinates>
            <CumulatedGroundDistance unit="NM">509</CumulatedGroundDistance>
        </Exit>
        <GreatCircleDistance unit="NM">424</GreatCircleDistance>
        <GroundDistance unit="NM">436</GroundDistance>
    </Airspace>
    <Airspace airspaceName="MILAN_UIR" airspaceType="UIR" airspaceICAOCode="LIMM">
        <Entry cumulatedFlightTime="PT1H11M32S">
            <Coordinates latitude="+156628" longitude="+50604">N4330.5 E01403.4</Coordinates>
            <CumulatedGroundDistance unit="NM">509</CumulatedGroundDistance>
        </Entry>
        <Exit cumulatedFlightTime="PT1H13M53S">
            <Coordinates  latitude="+157658" longitude="+51025">N4347.6 E01410.4</Coordinates>
            <CumulatedGroundDistance unit="NM">527</CumulatedGroundDistance>
        </Exit>
        <GreatCircleDistance unit="NM">497</GreatCircleDistance>
        <GroundDistance unit="NM">509</GroundDistance>
    </Airspace>
    <Airspace airspaceName="ZAGREB_FIR" airspaceType="FIR" airspaceICAOCode="LDZO">
        <Entry cumulatedFlightTime="PT1H13M52S">
            <Coordinates latitude="+157648" longitude="+51020">N4347.5 E01410.3</Coordinates>
            <CumulatedGroundDistance unit="NM">526</CumulatedGroundDistance>
        </Entry>
        <Exit cumulatedFlightTime="PT1H27M36S">
            <Coordinates  latitude="+163566" longitude="+53916">N4526.1 E01458.6</Coordinates>
            <CumulatedGroundDistance unit="NM">631</CumulatedGroundDistance>
        </Exit>
        <GreatCircleDistance unit="NM">514</GreatCircleDistance>
        <GroundDistance unit="NM">526</GroundDistance>
    </Airspace>
    <Airspace airspaceName="LJUBLJANA_FIR" airspaceType="FIR" airspaceICAOCode="LJLA">
        <Entry cumulatedFlightTime="PT1H27M36S">
            <Coordinates latitude="+163566" longitude="+53916">N4526.1 E01458.6</Coordinates>
            <CumulatedGroundDistance unit="NM">631</CumulatedGroundDistance>
        </Entry>
        <Exit cumulatedFlightTime="PT1H38M14S">
            <Coordinates  latitude="+168134" longitude="+56244">N4642.2 E01537.4</Coordinates>
            <CumulatedGroundDistance unit="NM">712</CumulatedGroundDistance>
        </Exit>
        <GreatCircleDistance unit="NM">619</GreatCircleDistance>
        <GroundDistance unit="NM">631</GroundDistance>
    </Airspace>
    <Airspace airspaceName="VIENNA_FIR" airspaceType="FIR" airspaceICAOCode="LOVV">
        <Entry cumulatedFlightTime="PT1H38M14S">
            <Coordinates latitude="+168134" longitude="+56244">N4642.2 E01537.4</Coordinates>
            <CumulatedGroundDistance unit="NM">712</CumulatedGroundDistance>
        </Entry>
        <Exit cumulatedFlightTime="PT1H55M31S">
            <Coordinates  latitude="+175451" longitude="+60484">N4844.2 E01648.1</Coordinates>
            <CumulatedGroundDistance unit="NM">843</CumulatedGroundDistance>
        </Exit>
        <GreatCircleDistance unit="NM">700</GreatCircleDistance>
        <GroundDistance unit="NM">712</GroundDistance>
    </Airspace>
    <Airspace airspaceName="PRAGUE_FIR" airspaceType="FIR" airspaceICAOCode="LKAA">
        <Entry cumulatedFlightTime="PT1H55M31S">
            <Coordinates latitude="+175451" longitude="+60484">N4844.2 E01648.1</Coordinates>
            <CumulatedGroundDistance unit="NM">843</CumulatedGroundDistance>
        </Entry>
        <Exit cumulatedFlightTime="PT2H8M00S">
            <Coordinates  latitude="+179941" longitude="+65434">N4959.0 E01810.6</Coordinates>
            <CumulatedGroundDistance unit="NM">936</CumulatedGroundDistance>
        </Exit>
        <GreatCircleDistance unit="NM">831</GreatCircleDistance>
        <GroundDistance unit="NM">843</GroundDistance>
    </Airspace>
    <Airspace airspaceName="WARSAW_FIR" airspaceType="FIR" airspaceICAOCode="EPWW">
        <Entry cumulatedFlightTime="PT2H8M00S">
            <Coordinates latitude="+179941" longitude="+65434">N4959.0 E01810.6</Coordinates>
            <CumulatedGroundDistance unit="NM">936</CumulatedGroundDistance>
        </Entry>
        <Exit cumulatedFlightTime="PT2H22M53S">
            <Coordinates  latitude="+181707" longitude="+68688">N5028.5 E01904.8</Coordinates>
            <CumulatedGroundDistance unit="NM">998</CumulatedGroundDistance>
        </Exit>
        <GreatCircleDistance unit="NM">920</GreatCircleDistance>
        <GroundDistance unit="NM">936</GroundDistance>
    </Airspace>
</AirspaceData>