<?xml version="1.0" encoding="utf-8"?>
<RegionWeatherBriefing creationTime="2024-10-26T23:14:51" fullPackage="true" xmlns="http://aeec.aviation-ia.net/633" xmlns:xsi="http://www.w3.org/2001/XMLSchema-instance" xsi:schemaLocation="http://aeec.aviation-ia.net/633 RegionWeatherBriefing.xsd">
    <M633Header timestamp="2024-10-26T23:14:51" versionNumber="3"/>
    <M633SupplementaryHeader>
        <Flight flightOriginDate="2024-10-27" scheduledTimeOfDeparture="2024-10-27T02:15:00Z">
            <FlightIdentification>
                <FlightIdentifier>LBT2972</FlightIdentifier>
                <FlightNumber airlineIATACode="BJ" number="2972">
                    <CommercialFlightNumber>BJ2972</CommercialFlightNumber>
                </FlightNumber>
            </FlightIdentification>
            <DepartureAirport>
                <AirportICAOCode>DTTJ</AirportICAOCode>
                <AirportIATACode>DJE</AirportIATACode>
            </DepartureAirport>
            <ArrivalAirport>
                <AirportICAOCode>EDDL</AirportICAOCode>
                <AirportIATACode>DUS</AirportIATACode>
            </ArrivalAirport>
        </Flight>
        <Aircraft aircraftRegistration="TSING">
            <AircraftModel>
                <AircraftICAOType>A320</AircraftICAOType>
            </AircraftModel>
        </Aircraft>
    </M633SupplementaryHeader>
    <RegionWeathers>
        <RegionWeather issuer="LIRR" type="AIRMET" startValidTime="2024-10-26T22:13:00" endValidTime="2024-10-27T02:13:00" observationTime="2024-10-26T22:11:00" sequence="1">
            <RegionWeatherText>
                <Paragraph sequence="1">
                    <Text>AIRMET 10 VALID 262213/260100 LIIB- LIRR ROMA FIR</Text>
                </Paragraph>
                <Paragraph sequence="2">
                    <Text>ISOL TS FCST WI N4142 E00944 - N4308 E00947 - N4334</Text>
                </Paragraph>
                <Paragraph sequence="3">
                    <Text>E01019 - N4342 E01100 - N4148 E01249 - N4142 E00944</Text>
                </Paragraph>
                <Paragraph sequence="4">
                    <Text>TOP ABV FL150 STNR NC=</Text>
                </Paragraph>
            </RegionWeatherText>
            <Location>
                <Airspaces>
                    <Airspace airspaceICAOCode="LIRR">
                        <AirspaceName>ROMA FIR</AirspaceName>
                    </Airspace>
                </Airspaces>
            </Location>
        </RegionWeather>
        <RegionWeather issuer="LIRR" type="AIRMET" startValidTime="2024-10-26T22:13:00" endValidTime="2024-10-27T02:13:00" observationTime="2024-10-26T22:10:00" sequence="2">
            <RegionWeatherText>
                <Paragraph sequence="1">
                    <Text>AIRMET 9 VALID 262213/260100 LIIB- LIRR ROMA FIR ISOL</Text>
                </Paragraph>
                <Paragraph sequence="2">
                    <Text>TS FCST WI N4142 E00944 - N4308 E00947 - N4334 E01019</Text>
                </Paragraph>
                <Paragraph sequence="3">
                    <Text>- N4342 E01100 - N4148 E01249 - N4142 E00944 TOP ABV</Text>
                </Paragraph>
                <Paragraph sequence="4">
                    <Text>FL150 STNR NC=</Text>
                </Paragraph>
            </RegionWeatherText>
            <Location>
                <Airspaces>
                    <Airspace airspaceICAOCode="LIRR">
                        <AirspaceName>ROMA FIR</AirspaceName>
                    </Airspace>
                </Airspaces>
            </Location>
        </RegionWeather>
        <RegionWeather issuer="LIMM" type="AIRMET" startValidTime="2024-10-27T01:00:00" endValidTime="2024-10-27T04:00:00" observationTime="2024-10-26T22:52:00" sequence="3">
            <RegionWeatherText>
                <Paragraph sequence="1">
                    <Text>AIRMET 47 VALID 270100/270400 LIIB- LIMM MILANO FIR</Text>
                </Paragraph>
                <Paragraph sequence="2">
                    <Text>OCNL TS FCST WI N4338 E01018 - N4503 E01014 - N4500</Text>
                </Paragraph>
                <Paragraph sequence="3">
                    <Text>E00643 - N4445 E00701 - N4431 E00652 - N4422 E00652 -</Text>
                </Paragraph>
                <Paragraph sequence="4">
                    <Text>N4407 E00718 - N4409 E00734 - N4401 E00743 - N4351</Text>
                </Paragraph>
                <Paragraph sequence="5">
                    <Text>E00728 - N4346 E00730 - N4310 E00942 - N4338 E01018</Text>
                </Paragraph>
                <Paragraph sequence="6">
                    <Text>TOP ABV FL150 STNR NC=</Text>
                </Paragraph>
            </RegionWeatherText>
            <Location>
                <Airspaces>
                    <Airspace airspaceICAOCode="LIMM">
                        <AirspaceName>MILANO FIR</AirspaceName>
                    </Airspace>
                </Airspaces>
            </Location>
        </RegionWeather>
        <RegionWeather issuer="LIMM" type="AIRMET" startValidTime="2024-10-27T01:00:00" endValidTime="2024-10-27T05:00:00" observationTime="2024-10-26T21:16:00" sequence="4">
            <RegionWeatherText>
                <Paragraph sequence="1">
                    <Text>AIRMET 46 VALID 270100/270500 LIIB- LIMM MILANO FIR</Text>
                </Paragraph>
                <Paragraph sequence="2">
                    <Text>SFC VIS 3000M BR FCST WI N4522 E00737 - N4446 E00728</Text>
                </Paragraph>
                <Paragraph sequence="3">
                    <Text>- N4422 E01025 - N4351 E01244 - N4427 E01201 - N4510</Text>
                </Paragraph>
                <Paragraph sequence="4">
                    <Text>E01004 - N4522 E00737 STNR NC=</Text>
                </Paragraph>
            </RegionWeatherText>
            <Location>
                <Airspaces>
                    <Airspace airspaceICAOCode="LIMM">
                        <AirspaceName>MILANO FIR</AirspaceName>
                    </Airspace>
                </Airspaces>
            </Location>
        </RegionWeather>
        <RegionWeather issuer="LIRR" type="SIGMET" startValidTime="2024-10-27T01:00:00" endValidTime="2024-10-27T04:00:00" observationTime="2024-10-26T22:51:00" sequence="5">
            <RegionWeatherText>
                <Paragraph sequence="1">
                    <Text>SIGMET 5 VALID 270100/270400 LIIB- LIRR ROMA FIR FRQ</Text>
                </Paragraph>
                <Paragraph sequence="2">
                    <Text>TS FCST W OF LINE N4130 E00934 - N3805 E00936 TOP</Text>
                </Paragraph>
                <Paragraph sequence="3">
                    <Text>FL380 STNR NC=</Text>
                </Paragraph>
            </RegionWeatherText>
            <Location>
                <Airspaces>
                    <Airspace airspaceICAOCode="LIRR">
                        <AirspaceName>ROMA FIR</AirspaceName>
                    </Airspace>
                </Airspaces>
            </Location>
        </RegionWeather>
        <RegionWeather issuer="LFMM" type="SIGMET" startValidTime="2024-10-26T23:00:00" endValidTime="2024-10-27T02:00:00" observationTime="2024-10-26T22:55:00" sequence="6">
            <RegionWeatherText>
                <Paragraph sequence="1">
                    <Text>SIGMET T23 VALID 262300/270200 LFPW- LFMM MARSEILLE</Text>
                </Paragraph>
                <Paragraph sequence="2">
                    <Text>FIR/UIR EMBD TS FCST WI N3900 E00800 - N4130 E00715 -</Text>
                </Paragraph>
                <Paragraph sequence="3">
                    <Text>N4300 E00600 - N4500 E00645 - N4430 E00700 - N4400</Text>
                </Paragraph>
                <Paragraph sequence="4">
                    <Text>E00700 - N4315 E00945 - N4115 E00945 - N4115 E00800 -</Text>
                </Paragraph>
                <Paragraph sequence="5">
                    <Text>N3945 E00800 - N3900 E00800 TOP FL400 STNR NC=</Text>
                </Paragraph>
            </RegionWeatherText>
            <Location>
                <Airspaces>
                    <Airspace airspaceICAOCode="LFMM">
                        <AirspaceName>MARSEILLE FIR/UIR</AirspaceName>
                    </Airspace>
                </Airspaces>
            </Location>
        </RegionWeather>
    </RegionWeathers>
</RegionWeatherBriefing>
